snowballstemmer/__init__.py
snowballstemmer/among.py
snowballstemmer/arabic_stemmer.py
snowballstemmer/armenian_stemmer.py
snowballstemmer/basestemmer.py
snowballstemmer/basque_stemmer.py
snowballstemmer/catalan_stemmer.py
snowballstemmer/danish_stemmer.py
snowballstemmer/dutch_porter_stemmer.py
snowballstemmer/dutch_stemmer.py
snowballstemmer/english_stemmer.py
snowballstemmer/esperanto_stemmer.py
snowballstemmer/estonian_stemmer.py
snowballstemmer/finnish_stemmer.py
snowballstemmer/french_stemmer.py
snowballstemmer/german_stemmer.py
snowballstemmer/greek_stemmer.py
snowballstemmer/hindi_stemmer.py
snowballstemmer/hungarian_stemmer.py
snowballstemmer/indonesian_stemmer.py
snowballstemmer/irish_stemmer.py
snowballstemmer/italian_stemmer.py
snowballstemmer/lithuanian_stemmer.py
snowballstemmer/nepali_stemmer.py
snowballstemmer/norwegian_stemmer.py
snowballstemmer/porter_stemmer.py
snowballstemmer/portuguese_stemmer.py
snowballstemmer/romanian_stemmer.py
snowballstemmer/russian_stemmer.py
snowballstemmer/serbian_stemmer.py
snowballstemmer/spanish_stemmer.py
snowballstemmer/swedish_stemmer.py
snowballstemmer/tamil_stemmer.py
snowballstemmer/turkish_stemmer.py
snowballstemmer/yiddish_stemmer.py
snowballstemmer-3.0.0.dist-info/licenses/COPYING
snowballstemmer-3.0.0.dist-info/METADATA
snowballstemmer-3.0.0.dist-info/WHEEL
snowballstemmer-3.0.0.dist-info/top_level.txt
snowballstemmer-3.0.0.dist-info/RECORD
